edison_client/__init__.py
edison_client/py.typed
edison_client/version.py
edison_client/clients/__init__.py
edison_client/clients/data_storage_methods.py
edison_client/clients/job_client.py
edison_client/clients/rest_client.py
edison_client/models/__init__.py
edison_client/models/app.py
edison_client/models/client.py
edison_client/models/data_storage_methods.py
edison_client/models/job_event.py
edison_client/models/rest.py
edison_client/utils/__init__.py
edison_client/utils/auth.py
edison_client/utils/general.py
edison_client/utils/module_utils.py
edison_client/utils/monitoring.py
edison_client/utils/world_model_tools.py
edison_client-0.8.4.dist-info/licenses/LICENSE
edison_client-0.8.4.dist-info/METADATA
edison_client-0.8.4.dist-info/WHEEL
edison_client-0.8.4.dist-info/top_level.txt
edison_client-0.8.4.dist-info/RECORD
