Metadata-Version: 2.4
Name: edison-client
Version: 0.8.4
Summary: A client for interacting with endpoints of the Edison Scientific service.
Author-email: Edison Scientific technical staff <hello@futurehouse.org>
License:                                  Apache License
Classifier: Operating System :: OS Independent
Classifier: Programming Language :: Python :: 3 :: Only
Classifier: Programming Language :: Python :: 3.11
Classifier: Programming Language :: Python :: 3.12
Classifier: Programming Language :: Python
Requires-Python: <3.14,>=3.11
License-File: LICENSE
Requires-Dist: aiofiles
Requires-Dist: cloudpickle
Requires-Dist: fhaviary
Requires-Dist: google-resumable-media
Requires-Dist: httpx
Requires-Dist: httpx-aiohttp
Requires-Dist: ldp>=0.22.0
Requires-Dist: litellm
Requires-Dist: openai>=2.7
Requires-Dist: pydantic
Requires-Dist: python-dotenv
Requires-Dist: requests
Requires-Dist: tenacity
Requires-Dist: tqdm>=4.62
Provides-Extra: dev
Requires-Dist: black; extra == "dev"
Requires-Dist: edison-client[monitoring,typing]; extra == "dev"
Requires-Dist: ipykernel; extra == "dev"
Requires-Dist: jupyter; extra == "dev"
Requires-Dist: jupyterlab; extra == "dev"
Requires-Dist: mypy; extra == "dev"
Requires-Dist: notebook; extra == "dev"
Requires-Dist: pre-commit; extra == "dev"
Requires-Dist: pylint-per-file-ignores; extra == "dev"
Requires-Dist: pylint-pydantic; extra == "dev"
Requires-Dist: pylint>=4; extra == "dev"
Requires-Dist: pytest; extra == "dev"
Requires-Dist: pytest-asyncio; extra == "dev"
Requires-Dist: pytest-rerunfailures; extra == "dev"
Requires-Dist: pytest-subtests; extra == "dev"
Requires-Dist: pytest-timeout; extra == "dev"
Requires-Dist: pytest-timer[colorama]; extra == "dev"
Requires-Dist: pytest-xdist; extra == "dev"
Requires-Dist: ruff; extra == "dev"
Requires-Dist: setuptools_scm; extra == "dev"
Provides-Extra: monitoring
Requires-Dist: newrelic<12.0.0,>=11.0.0; extra == "monitoring"
Provides-Extra: typing
Requires-Dist: types-PyYAML; extra == "typing"
Requires-Dist: types-aiofiles; extra == "typing"
Requires-Dist: types-requests; extra == "typing"
Requires-Dist: types-tqdm; extra == "typing"
Dynamic: license-file
